webloop/__init__.py
webloop/auth.py
webloop/cli.py
webloop/core.py
webloop/nanohtml.py
webloop/orm.py
webloop-0.1.0.dist-info/METADATA
webloop-0.1.0.dist-info/WHEEL
webloop-0.1.0.dist-info/top_level.txt
webloop-0.1.0.dist-info/RECORD
