Metadata-Version: 2.4
Name: webloop
Version: 0.1.0
Summary: Flask-inspired Python web framework with ORM, Auth, and NanoHTML.
Author: Aftab Alam
Author-email: Your Name <you@example.com>
Project-URL: Homepage, https://pypi.org/project/webloop/
Requires-Python: >=3.8
Dynamic: author
Dynamic: requires-python
